{"code": {"code": {"1": {"disc": 2.0, "code": 1.0, "requ": 0.0, "frq": {"1": 1.5, "3": "", "2": ""}, "skill_limit": {"1": 2.0, "3": "", "2": ""}, "att": {"1": 1.0, "3": "", "2": ""}, "range": {"1": 90.0, "3": "", "2": ""}, "cost": {"1": 80.0, "3": "", "2": ""}, "recy": {"1": 64.0, "3": 0.0, "2": 0.0}, "attn": {"1": 3.0, "3": "", "2": ""}}, "2": {"disc": 2.0, "code": 2.0, "requ": 4.0, "frq": {"1": 1.5, "3": "", "2": ""}, "skill_limit": {"1": 2.0, "3": "", "2": ""}, "att": {"1": 1.0, "3": "", "2": ""}, "range": {"1": 90.0, "3": "", "2": ""}, "cost": {"1": 80.0, "3": "", "2": ""}, "recy": {"1": 64.0, "3": 0.0, "2": 0.0}, "attn": {"1": 3.0, "3": "", "2": ""}}, "3": {"disc": 2.0, "code": 3.0, "requ": 5.0, "frq": {"1": 1.5, "3": "", "2": ""}, "skill_limit": {"1": 2.0, "3": "", "2": ""}, "att": {"1": 1.0, "3": "", "2": ""}, "range": {"1": 90.0, "3": "", "2": ""}, "cost": {"1": 80.0, "3": "", "2": ""}, "recy": {"1": 64.0, "3": 0.0, "2": 0.0}, "attn": {"1": 3.0, "3": "", "2": ""}}, "4": {"disc": 3.0, "code": 4.0, "requ": 6.0, "frq": {"1": 1.5, "3": "", "2": ""}, "skill_limit": {"1": 2.0, "3": "", "2": ""}, "att": {"1": 1.0, "3": "", "2": ""}, "range": {"1": 90.0, "3": "", "2": ""}, "cost": {"1": 80.0, "3": "", "2": ""}, "recy": {"1": 64.0, "3": 0.0, "2": 0.0}, "attn": {"1": 3.0, "3": "", "2": ""}}, "5": {"disc": 3.0, "code": 5.0, "requ": 7.0, "frq": {"1": 1.5, "3": "", "2": 1.2}, "skill_limit": {"1": 3.0, "3": "", "2": ""}, "att": {"1": 1.0, "3": "", "2": 4.0}, "range": {"1": 90.0, "3": "", "2": 100.0}, "cost": {"1": 80.0, "3": "", "2": 120.0}, "recy": {"1": 64.0, "3": 0.0, "2": 96.0}, "attn": {"1": 3.0, "3": "", "2": 6.0}}, "6": {"disc": 4.0, "code": 6.0, "requ": 8.0, "frq": {"1": 1.5, "3": "", "2": 1.2}, "skill_limit": {"1": 3.0, "3": "", "2": ""}, "att": {"1": 1.0, "3": "", "2": 4.0}, "range": {"1": 90.0, "3": "", "2": 100.0}, "cost": {"1": 80.0, "3": "", "2": 120.0}, "recy": {"1": 64.0, "3": 0.0, "2": 96.0}, "attn": {"1": 3.0, "3": "", "2": 6.0}}, "7": {"disc": 4.0, "code": 7.0, "requ": 9.0, "frq": {"1": 1.5, "3": "", "2": 1.2}, "skill_limit": {"1": 3.0, "3": "", "2": ""}, "att": {"1": 1.0, "3": "", "2": 4.0}, "range": {"1": 90.0, "3": "", "2": 100.0}, "cost": {"1": 80.0, "3": "", "2": 120.0}, "recy": {"1": 64.0, "3": 0.0, "2": 96.0}, "attn": {"1": 3.0, "3": "", "2": 6.0}}, "8": {"disc": 5.0, "code": 8.0, "requ": 10.0, "frq": {"1": 1.5, "3": "", "2": 1.2}, "skill_limit": {"1": 3.0, "3": "", "2": ""}, "att": {"1": 1.0, "3": "", "2": 4.0}, "range": {"1": 90.0, "3": "", "2": 100.0}, "cost": {"1": 80.0, "3": "", "2": 120.0}, "recy": {"1": 64.0, "3": 0.0, "2": 96.0}, "attn": {"1": 4.0, "3": "", "2": 6.0}}, "9": {"disc": 5.0, "code": 9.0, "requ": 11.0, "frq": {"1": 1.5, "3": "", "2": 1.2}, "skill_limit": {"1": 3.0, "3": "", "2": ""}, "att": {"1": 1.0, "3": "", "2": 4.0}, "range": {"1": 90.0, "3": "", "2": 100.0}, "cost": {"1": 80.0, "3": "", "2": 120.0}, "recy": {"1": 64.0, "3": 0.0, "2": 96.0}, "attn": {"1": 4.0, "3": "", "2": 6.0}}, "10": {"disc": 6.0, "code": 10.0, "requ": 12.0, "frq": {"1": 1.5, "3": "", "2": 1.2}, "skill_limit": {"1": 4.0, "3": "", "2": ""}, "att": {"1": 1.0, "3": "", "2": 4.0}, "range": {"1": 90.0, "3": "", "2": 100.0}, "cost": {"1": 80.0, "3": "", "2": 120.0}, "recy": {"1": 64.0, "3": 0.0, "2": 96.0}, "attn": {"1": 4.0, "3": "", "2": 6.0}}, "11": {"disc": 7.0, "code": 11.0, "requ": 13.0, "frq": {"1": 1.5, "3": "", "2": 1.2}, "skill_limit": {"1": 4.0, "3": "", "2": ""}, "att": {"1": 1.0, "3": "", "2": 4.0}, "range": {"1": 90.0, "3": "", "2": 100.0}, "cost": {"1": 80.0, "3": "", "2": 120.0}, "recy": {"1": 64.0, "3": 0.0, "2": 96.0}, "attn": {"1": 4.0, "3": "", "2": 6.0}}, "12": {"disc": 8.0, "code": 12.0, "requ": 14.0, "frq": {"1": 1.5, "3": 0.8, "2": 1.2}, "skill_limit": {"1": 4.0, "3": "", "2": ""}, "att": {"1": 1.0, "3": 10.0, "2": 4.0}, "range": {"1": 90.0, "3": 105.0, "2": 100.0}, "cost": {"1": 80.0, "3": 140.0, "2": 120.0}, "recy": {"1": 64.0, "3": 112.0, "2": 96.0}, "attn": {"1": 4.0, "3": 8.0, "2": 6.0}}, "13": {"disc": 9.0, "code": 13.0, "requ": 15.0, "frq": {"1": 1.5, "3": 0.8, "2": 1.1}, "skill_limit": {"1": 4.0, "3": "", "2": ""}, "att": {"1": 1.0, "3": 10.0, "2": 4.0}, "range": {"1": 90.0, "3": 105.0, "2": 100.0}, "cost": {"1": 80.0, "3": 140.0, "2": 120.0}, "recy": {"1": 64.0, "3": 112.0, "2": 96.0}, "attn": {"1": 4.0, "3": 8.0, "2": 6.0}}, "14": {"disc": 10.0, "code": 14.0, "requ": 16.0, "frq": {"1": 1.5, "3": 0.8, "2": 1.1}, "skill_limit": {"1": 5.0, "3": "", "2": ""}, "att": {"1": 1.0, "3": 10.0, "2": 5.0}, "range": {"1": 90.0, "3": 105.0, "2": 100.0}, "cost": {"1": 80.0, "3": 140.0, "2": 120.0}, "recy": {"1": 64.0, "3": 112.0, "2": 96.0}, "attn": {"1": 4.0, "3": 8.0, "2": 6.0}}, "15": {"disc": 11.0, "code": 15.0, "requ": 17.0, "frq": {"1": 1.5, "3": 0.8, "2": 1.1}, "skill_limit": {"1": 5.0, "3": "", "2": ""}, "att": {"1": 1.0, "3": 10.0, "2": 5.0}, "range": {"1": 90.0, "3": 105.0, "2": 100.0}, "cost": {"1": 80.0, "3": 140.0, "2": 120.0}, "recy": {"1": 64.0, "3": 112.0, "2": 96.0}, "attn": {"1": 4.0, "3": 8.0, "2": 7.0}}, "16": {"disc": 12.0, "code": 16.0, "requ": 18.0, "frq": {"1": 1.5, "3": 0.8, "2": 1.1}, "skill_limit": {"1": 5.0, "3": "", "2": ""}, "att": {"1": 2.0, "3": 10.0, "2": 5.0}, "range": {"1": 90.0, "3": 105.0, "2": 100.0}, "cost": {"1": 80.0, "3": 140.0, "2": 120.0}, "recy": {"1": 64.0, "3": 112.0, "2": 96.0}, "attn": {"1": 4.0, "3": 9.0, "2": 7.0}}, "17": {"disc": 13.0, "code": 17.0, "requ": 19.0, "frq": {"1": 1.4, "3": 0.8, "2": 1.1}, "skill_limit": {"1": 5.0, "3": "", "2": ""}, "att": {"1": 2.0, "3": 10.0, "2": 5.0}, "range": {"1": 90.0, "3": 105.0, "2": 100.0}, "cost": {"1": 80.0, "3": 140.0, "2": 120.0}, "recy": {"1": 64.0, "3": 112.0, "2": 96.0}, "attn": {"1": 5.0, "3": 9.0, "2": 7.0}}, "18": {"disc": 14.0, "code": 18.0, "requ": 20.0, "frq": {"1": 1.4, "3": 0.8, "2": 1.1}, "skill_limit": {"1": 6.0, "3": "", "2": ""}, "att": {"1": 2.0, "3": 10.0, "2": 5.0}, "range": {"1": 90.0, "3": 105.0, "2": 100.0}, "cost": {"1": 80.0, "3": 140.0, "2": 120.0}, "recy": {"1": 64.0, "3": 112.0, "2": 96.0}, "attn": {"1": 5.0, "3": 9.0, "2": 7.0}}, "19": {"disc": 15.0, "code": 19.0, "requ": 21.0, "frq": {"1": 1.4, "3": 0.8, "2": 1.1}, "skill_limit": {"1": 6.0, "3": "", "2": ""}, "att": {"1": 2.0, "3": 10.0, "2": 5.0}, "range": {"1": 90.0, "3": 105.0, "2": 100.0}, "cost": {"1": 80.0, "3": 140.0, "2": 120.0}, "recy": {"1": 64.0, "3": 112.0, "2": 96.0}, "attn": {"1": 5.0, "3": 9.0, "2": 7.0}}, "20": {"disc": 16.0, "code": 20.0, "requ": 22.0, "frq": {"1": 1.4, "3": 0.8, "2": 1.1}, "skill_limit": {"1": 6.0, "3": "", "2": ""}, "att": {"1": 2.0, "3": 12.0, "2": 5.0}, "range": {"1": 90.0, "3": 105.0, "2": 100.0}, "cost": {"1": 80.0, "3": 140.0, "2": 120.0}, "recy": {"1": 64.0, "3": 112.0, "2": 96.0}, "attn": {"1": 5.0, "3": 9.0, "2": 7.0}}, "21": {"disc": 17.0, "code": 21.0, "requ": 23.0, "frq": {"1": 1.4, "3": 0.8, "2": 1.1}, "skill_limit": {"1": 7.0, "3": "", "2": ""}, "att": {"1": 2.0, "3": 12.0, "2": 5.0}, "range": {"1": 90.0, "3": 105.0, "2": 100.0}, "cost": {"1": 80.0, "3": 140.0, "2": 120.0}, "recy": {"1": 64.0, "3": 112.0, "2": 96.0}, "attn": {"1": 5.0, "3": 9.0, "2": 7.0}}, "22": {"disc": 18.0, "code": 22.0, "requ": 24.0, "frq": {"1": 1.4, "3": 0.8, "2": 1.1}, "skill_limit": {"1": 7.0, "3": "", "2": ""}, "att": {"1": 2.0, "3": 12.0, "2": 5.0}, "range": {"1": 90.0, "3": 105.0, "2": 100.0}, "cost": {"1": 80.0, "3": 140.0, "2": 120.0}, "recy": {"1": 64.0, "3": 112.0, "2": 96.0}, "attn": {"1": 5.0, "3": 9.0, "2": 7.0}}, "23": {"disc": 19.0, "code": 23.0, "requ": 25.0, "frq": {"1": 1.4, "3": 0.8, "2": 1.1}, "skill_limit": {"1": 7.0, "3": "", "2": ""}, "att": {"1": 2.0, "3": 12.0, "2": 6.0}, "range": {"1": 90.0, "3": 105.0, "2": 100.0}, "cost": {"1": 80.0, "3": 140.0, "2": 120.0}, "recy": {"1": 64.0, "3": 112.0, "2": 96.0}, "attn": {"1": 5.0, "3": 9.0, "2": 7.0}}, "24": {"disc": 20.0, "code": 24.0, "requ": 26.0, "frq": {"1": 1.3, "3": 0.7, "2": 1.0}, "skill_limit": {"1": 8.0, "3": "", "2": ""}, "att": {"1": 2.0, "3": 12.0, "2": 6.0}, "range": {"1": 90.0, "3": 105.0, "2": 100.0}, "cost": {"1": 80.0, "3": 140.0, "2": 120.0}, "recy": {"1": 64.0, "3": 112.0, "2": 96.0}, "attn": {"1": 5.0, "3": 9.0, "2": 8.0}}, "25": {"disc": 21.0, "code": 25.0, "requ": 27.0, "frq": {"1": 1.3, "3": 0.7, "2": 1.0}, "skill_limit": {"1": 8.0, "3": "", "2": ""}, "att": {"1": 2.0, "3": 14.0, "2": 6.0}, "range": {"1": 90.0, "3": 105.0, "2": 100.0}, "cost": {"1": 80.0, "3": 140.0, "2": 120.0}, "recy": {"1": 64.0, "3": 112.0, "2": 96.0}, "attn": {"1": 5.0, "3": 10.0, "2": 8.0}}, "26": {"disc": 22.0, "code": 26.0, "requ": 28.0, "frq": {"1": 1.3, "3": 0.7, "2": 1.0}, "skill_limit": {"1": 8.0, "3": "", "2": ""}, "att": {"1": 2.0, "3": 14.0, "2": 6.0}, "range": {"1": 90.0, "3": 105.0, "2": 100.0}, "cost": {"1": 80.0, "3": 140.0, "2": 120.0}, "recy": {"1": 64.0, "3": 112.0, "2": 96.0}, "attn": {"1": 5.0, "3": 10.0, "2": 8.0}}, "27": {"disc": 23.0, "code": 27.0, "requ": 29.0, "frq": {"1": 1.3, "3": 0.7, "2": 1.0}, "skill_limit": {"1": 9.0, "3": "", "2": ""}, "att": {"1": 2.0, "3": 14.0, "2": 6.0}, "range": {"1": 90.0, "3": 105.0, "2": 100.0}, "cost": {"1": 80.0, "3": 140.0, "2": 120.0}, "recy": {"1": 64.0, "3": 112.0, "2": 96.0}, "attn": {"1": 5.0, "3": 10.0, "2": 8.0}}, "28": {"disc": 24.0, "code": 28.0, "requ": 30.0, "frq": {"1": 1.3, "3": 0.7, "2": 1.0}, "skill_limit": {"1": 9.0, "3": "", "2": ""}, "att": {"1": 2.0, "3": 14.0, "2": 6.0}, "range": {"1": 90.0, "3": 105.0, "2": 100.0}, "cost": {"1": 80.0, "3": 140.0, "2": 120.0}, "recy": {"1": 64.0, "3": 112.0, "2": 96.0}, "attn": {"1": 5.0, "3": 10.0, "2": 8.0}}, "29": {"disc": 25.0, "code": 29.0, "requ": 31.0, "frq": {"1": 1.3, "3": 0.7, "2": 1.0}, "skill_limit": {"1": 10.0, "3": "", "2": ""}, "att": {"1": 2.0, "3": 14.0, "2": 6.0}, "range": {"1": 90.0, "3": 105.0, "2": 100.0}, "cost": {"1": 80.0, "3": 140.0, "2": 120.0}, "recy": {"1": 64.0, "3": 112.0, "2": 96.0}, "attn": {"1": 5.0, "3": 11.0, "2": 9.0}}, "30": {"disc": 26.0, "code": 30.0, "requ": 32.0, "frq": {"1": 1.3, "3": 0.7, "2": 1.0}, "skill_limit": {"1": 10.0, "3": "", "2": ""}, "att": {"1": 2.0, "3": 14.0, "2": 6.0}, "range": {"1": 90.0, "3": 105.0, "2": 100.0}, "cost": {"1": 80.0, "3": 140.0, "2": 120.0}, "recy": {"1": 64.0, "3": 112.0, "2": 96.0}, "attn": {"1": 5.0, "3": 12.0, "2": 9.0}}}, "star": {"1": {"1": {"code": 1.0}, "2": {"code": 2.0}, "3": {"code": 3.0}, "4": {"code": 4.0}, "5": {"code": 5.0}, "6": {"code": 6.0}, "len": 6}, "3": {"1": {"code": 12.0}, "2": {"code": 13.0}, "3": {"code": 14.0}, "4": {"code": 15.0}, "5": {"code": 16.0}, "6": {"code": 17.0}, "7": {"code": 18.0}, "8": {"code": 19.0}, "9": {"code": 20.0}, "10": {"code": 21.0}, "11": {"code": 22.0}, "len": 11}, "2": {"1": {"code": 5.0}, "2": {"code": 6.0}, "3": {"code": 7.0}, "4": {"code": 8.0}, "5": {"code": 9.0}, "6": {"code": 10.0}, "7": {"code": 11.0}, "8": {"code": 12.0}, "9": {"code": 13.0}, "len": 9}, "5": {"1": {"code": 26.0}, "2": {"code": 27.0}, "3": {"code": 28.0}, "4": {"code": 29.0}, "5": {"code": 30.0}, "len": 5}, "4": {"1": {"code": 19.0}, "2": {"code": 20.0}, "3": {"code": 21.0}, "4": {"code": 22.0}, "5": {"code": 23.0}, "6": {"code": 24.0}, "7": {"code": 25.0}, "8": {"code": 26.0}, "len": 8}}}, "main": {"skill_1": "", "avatar_sprite_frame_name": "Icon/ICON_TowerLeiZhenZi", "face_left": 1, "name": "雷震子", "skill_3": "", "star_count": 5.0, "attack_range_type": "circle", "nameh": "雷\n震\n子", "skill_2": "", "code_count": 30.0, "type": "hero", "id": "tower_leizhenzi", "icon_sprite_frame_name": "Icon/ICON_Tower_LeiZhenZi01"}, "star": {"1": {"ccbi": {"1": "CTL_Tower_LeiZhenZi", "3": "", "2": ""}, "skill": {}, "star": 1.0, "upgrade_need_count": 2.0}, "2": {"ccbi": {"1": "CTL_Tower_LeiZhenZi", "3": "", "2": "CTL_Tower_LeiZhenZi"}, "skill": {"s_leizhenzi_build": {}}, "star": 2.0, "upgrade_need_count": 2.0}, "3": {"ccbi": {"1": "CTL_Tower_LeiZhenZi", "3": "CTL_Tower_LeiZhenZi", "2": "CTL_Tower_LeiZhenZi"}, "skill": {"s_leizhenzi_build": {}}, "star": 3.0, "upgrade_need_count": 3.0}, "4": {"ccbi": {"1": "CTL_Tower_LeiZhenZi", "3": "CTL_Tower_LeiZhenZi", "2": "CTL_Tower_LeiZhenZi"}, "skill": {"s_leizhenzi_build": {}}, "star": 4.0, "upgrade_need_count": 3.0}, "5": {"ccbi": {"1": "CTL_Tower_LeiZhenZi", "3": "CTL_Tower_LeiZhenZi", "2": "CTL_Tower_LeiZhenZi"}, "skill": {"s_leizhenzi_build": {}}, "star": 5.0, "upgrade_need_count": ""}}}